cvkit/__init__.py
cvkit/__version__.py
cvkit/plots.py
cvkit/projection.py
cvkit/slam.py
cvkit/utils/__init__.py
cvkit/utils/io.py
cvkit/utils/math.py
cvkit-0.1.0.dist-info/LICENSE
cvkit-0.1.0.dist-info/METADATA
cvkit-0.1.0.dist-info/WHEEL
cvkit-0.1.0.dist-info/top_level.txt
cvkit-0.1.0.dist-info/RECORD
