Metadata-Version: 2.1
Name: cvkit
Version: 0.1.0
Summary: Multiple view geometry and other Computer Vision algorithms implemented in Python.
Home-page: https://github.com/jan-mue/cvkit
Author: Jan Müller
Author-email: 
License: MIT
Platform: UNKNOWN
Classifier: License :: OSI Approved :: MIT License
Classifier: Programming Language :: Python
Classifier: Programming Language :: Python :: 3
Classifier: Programming Language :: Python :: Implementation :: CPython
Classifier: Programming Language :: Python :: Implementation :: PyPy
Requires-Python: >=3.5.0
Requires-Dist: geometer (==0.2)
Requires-Dist: scikit-image
Requires-Dist: scipy
Requires-Dist: matplotlib
Requires-Dist: meshio
